setuptools_gettext/__init__.py
setuptools_gettext-0.1.14.dist-info/COPYING
setuptools_gettext-0.1.14.dist-info/METADATA
setuptools_gettext-0.1.14.dist-info/WHEEL
setuptools_gettext-0.1.14.dist-info/entry_points.txt
setuptools_gettext-0.1.14.dist-info/top_level.txt
setuptools_gettext-0.1.14.dist-info/zip-safe
setuptools_gettext-0.1.14.dist-info/RECORD
