Metadata-Version: 2.1
Name: setuptools-gettext
Version: 0.1.14
Summary: Setuptools gettext extension plugin
Maintainer-email: Breezy Developers <breezy-core@googlegroups.com>
Project-URL: Homepage, https://github.com/breezy-team/setuptools-gettext
Project-URL: repository, https://github.com/breezy-team/setuptools-gettext.git
Keywords: setuptools,gettext
Classifier: Topic :: Software Development :: Version Control
Classifier: License :: OSI Approved :: GNU General Public License v2 or later (GPLv2+)
Classifier: Intended Audience :: Developers
Classifier: Programming Language :: Python :: 3
Classifier: Programming Language :: Python :: 3.8
Classifier: Programming Language :: Python :: 3.9
Classifier: Programming Language :: Python :: 3.10
Classifier: Programming Language :: Python :: 3.11
Classifier: Programming Language :: Python :: 3.12
Classifier: Operating System :: POSIX
Classifier: Operating System :: MacOS :: MacOS X
Classifier: Operating System :: Microsoft :: Windows
Requires-Python: >=3.8
License-File: COPYING
Requires-Dist: setuptools >=60.8
Requires-Dist: tomli >=1.2.1 ; python_version < "3.11"
Provides-Extra: dev
Requires-Dist: ruff ==0.4.3 ; extra == 'dev'
